modoboa_pfxadmin_migrate/__init__.py
modoboa_pfxadmin_migrate/models.py
modoboa_pfxadmin_migrate/management/__init__.py
modoboa_pfxadmin_migrate/management/commands/__init__.py
modoboa_pfxadmin_migrate/management/commands/migrate_from_postfixadmin.py
modoboa_pfxadmin_migrate-1.1.2.dist-info/LICENSE
modoboa_pfxadmin_migrate-1.1.2.dist-info/METADATA
modoboa_pfxadmin_migrate-1.1.2.dist-info/WHEEL
modoboa_pfxadmin_migrate-1.1.2.dist-info/top_level.txt
modoboa_pfxadmin_migrate-1.1.2.dist-info/RECORD
